orderby/__init__.py
orderby/sorter.py
orderby/tests/__init__.py
orderby/tests/test_api.py
orderby/tests/test_sorter.py
orderby-0.0.2.dist-info/DESCRIPTION.rst
orderby-0.0.2.dist-info/METADATA
orderby-0.0.2.dist-info/RECORD
orderby-0.0.2.dist-info/WHEEL
orderby-0.0.2.dist-info/metadata.json
orderby-0.0.2.dist-info/top_level.txt
